mlgebra/MLgebra.py
mlgebra/__init__.py
mlgebra/exception.py
mlgebra/layer.py
mlgebra/losses.py
mlgebra/model.py
mlgebra/neuron.py
mlgebra-1.1.0.dist-info/LICENSE.txt
mlgebra-1.1.0.dist-info/METADATA
mlgebra-1.1.0.dist-info/WHEEL
mlgebra-1.1.0.dist-info/top_level.txt
mlgebra-1.1.0.dist-info/RECORD
