Metadata-Version: 2.1
Name: mlgebra
Version: 1.1.0
Summary: A machine learning tool for Python, in Python
Author: Ahmet Erdem
Classifier: Programming Language :: Python :: 3
Classifier: License :: OSI Approved :: MIT License
Classifier: Operating System :: OS Independent
Requires-Python: >=3.9
License-File: LICENSE.txt
Requires-Dist: vectorgebra >=3.1.0
